m12/__init__.py
m12/months.py
m12-0.0.1.dist-info/LICENSE
m12-0.0.1.dist-info/METADATA
m12-0.0.1.dist-info/WHEEL
m12-0.0.1.dist-info/entry_points.txt
m12-0.0.1.dist-info/top_level.txt
m12-0.0.1.dist-info/RECORD
