Metadata-Version: 2.1
Name: m12
Version: 0.0.1
Summary: Template
Home-page: https://github.com/microprediction/m12
Author: microprediction
Author-email: pcotton@intechinvestments.com
License: MIT
Platform: UNKNOWN
Classifier: License :: OSI Approved :: MIT License
Classifier: Programming Language :: Python :: 3
Classifier: Programming Language :: Python :: 3.7
Requires-Dist: wheel
Requires-Dist: pathlib
